{
    "pnr": "TRH-UK-PNR-339888K546",
    "totalApplicants": 1,
    "applicants": [
        {
            "pnr": "TRH-UK-PNR-339888K546",
            "user_pnr": "TRH-UK-PNR-339888K546-APPT-001",
            "completed": true,
            "passportInfo": [],
            "nidInfo": {
                "has_nid": null
            },
            "contactInfo": {
                "emails": [
                    ""
                ],
                "phones": [
                    ""
                ],
                "addresses": [
                    {
                        "line1": "",
                        "line2": "",
                        "city": "",
                        "state": "",
                        "postalCode": "",
                        "isCorrespondence": false,
                        "livedInFor": "",
                        "ownershipStatus": ""
                    }
                ],
                "preferred_phone_no": ""
            },
            "familyInfo": {
                "relationshipStatus": "",
                "familyMembers": [],
                "hasRelativeInUK": null,
                "relativeAddress": {
                    "line1": "",
                    "line2": "",
                    "city": "",
                    "state": "",
                    "postalCode": ""
                }
            },
            "accommodationDetails": {
                "hasAddress": null,
                "hotels": [
                    ""
                ],
                "addresses": [
                    {
                        "line1": "",
                        "line2": "",
                        "city": "",
                        "state": "",
                        "postalCode": ""
                    }
                ]
            },
            "employmentInfo": {
                "employmentStatus": "",
                "jobDetails": "",
                "yearlyEarning": "",
                "jobTitle": "",
                "monthlyIncome": "",
                "jobDescription": ""
            },
            "incomeExpenditure": {
                "haveSavings": null,
                "planningToExpense": "",
                "totalExpenseInBd": "",
                "paymentInfo": [
                    {
                        "currency": "",
                        "amount": "",
                        "paidFor": ""
                    }
                ]
            },
            "travelInfo": {
                "visitMainReason": "",
                "businessReasonToVisitUk": "",
                "tourismReasonToVisitUk": "",
                "activities": "",
                "arrivalDate": "",
                "leaveDate": ""
            },
            "travelHistory": []
        }
    ],
    "status": "completed",
    "timestamp": "2025-11-17T12:09:20.530Z"
}